stemu/__init__.py
stemu/_version.py
stemu/emu.py
stemu/skutils.py
stemu/utils.py
stemu-0.0.1.dist-info/LICENSE
stemu-0.0.1.dist-info/METADATA
stemu-0.0.1.dist-info/WHEEL
stemu-0.0.1.dist-info/top_level.txt
stemu-0.0.1.dist-info/RECORD
